CHANGES.txt
MANIFEST.in
README.md
setup.cfg
setup.py
por/__init__.py
por.gdata.egg-info/PKG-INFO
por.gdata.egg-info/SOURCES.txt
por.gdata.egg-info/dependency_links.txt
por.gdata.egg-info/entry_points.txt
por.gdata.egg-info/namespace_packages.txt
por.gdata.egg-info/not-zip-safe
por.gdata.egg-info/requires.txt
por.gdata.egg-info/top_level.txt
por/gdata/__init__.py
por/gdata/utils.py
por/gdata/views.py
por/gdata/skins/fallback.pt
por/gdata/skins/fallback_admin.pt
por/gdata/skins/manage_iterations.pt
por/gdata/skins/view_iterations.pt
por/gdata/uploads/project_template.ods