Metadata-Version: 1.0
Name: por.gdata
Version: 1.7.2
Summary: Penelope gdata integration
Home-page: http://getpenelope.github.com
Author: Penelope Team
Author-email: penelopedev@redturtle.it
License: UNKNOWN
Keywords: web wsgi bfg pylons pyramid
Platform: UNKNOWN
Classifier: Programming Language :: Python
Classifier: Framework :: Pylons
Classifier: Topic :: Internet :: WWW/HTTP
Classifier: Topic :: Internet :: WWW/HTTP :: WSGI :: Application
